nxarray/__init__.py
nxarray/_accessors.py
nxarray/_core.py
nxarray/_version.py
nxarray-0.4.7.dist-info/licenses/LICENSE
nxarray-0.4.7.dist-info/METADATA
nxarray-0.4.7.dist-info/WHEEL
nxarray-0.4.7.dist-info/top_level.txt
nxarray-0.4.7.dist-info/RECORD
