Metadata-Version: 2.4
Name: nxarray
Version: 0.4.7
Summary: xarray extension for NeXus input/output.
Author-email: Mirco Panighel <mirkopanighel@gmail.com>
License-Expression: MIT
Project-URL: Homepage, https://github.com/nxarray/nxarray
Project-URL: Issues, https://github.com/nxarray/nxarray/issues
Classifier: Development Status :: 4 - Beta
Classifier: Intended Audience :: Science/Research
Classifier: Natural Language :: English
Classifier: Programming Language :: Python :: 3
Classifier: Operating System :: OS Independent
Requires-Python: >=3.8
License-File: LICENSE
Dynamic: license-file
